setup.py
virustotal.py
virustotal.egg-info/PKG-INFO
virustotal.egg-info/SOURCES.txt
virustotal.egg-info/dependency_links.txt
virustotal.egg-info/top_level.txt