Metadata-Version: 1.0
Name: virustotal
Version: 1.0.2
Summary: Pythonic VirusTotal Public API 2.0 client
Home-page: https://github.com/gawen/virustotal
Author: Gawen Arab
Author-email: g@wenarab.com
License: MIT
Platform: UNKNOWN
Classifier: Development Status :: 4 - Beta
Classifier: Environment :: Console
Classifier: Intended Audience :: Developers
Classifier: Intended Audience :: System Administrators
Classifier: License :: OSI Approved :: MIT License
Classifier: Programming Language :: Python
Classifier: Topic :: Security
Classifier: Topic :: Software Development :: Libraries :: Python Modules
